psds_eval/__init__.py
psds_eval/psds.py
psds_eval/version.py
psds_eval-0.5.3.dist-info/LICENSE
psds_eval-0.5.3.dist-info/METADATA
psds_eval-0.5.3.dist-info/WHEEL
psds_eval-0.5.3.dist-info/top_level.txt
psds_eval-0.5.3.dist-info/RECORD
