Metadata-Version: 2.1
Name: psds-eval
Version: 0.5.3
Summary: A module to calculate Polyphonic Sound Detection Score
Home-page: UNKNOWN
License: MIT
Keywords: polyphonic sound detection evaluation score
Platform: UNKNOWN
Requires-Python: >=3.6
Requires-Dist: pandas (>=0.19)
Requires-Dist: numpy (>=1.9.0)
Requires-Dist: matplotlib (>=3.1.0)
Requires-Dist: pytest (>=4.3)
